CubaCrawler/Cubadebate.py
CubaCrawler/Granma.py
CubaCrawler/ScrapBase.py
CubaCrawler/__init__.py
CubaCrawler/crawler.py
CubaCrawler-1.0.0.dist-info/LICENSE
CubaCrawler-1.0.0.dist-info/METADATA
CubaCrawler-1.0.0.dist-info/WHEEL
CubaCrawler-1.0.0.dist-info/top_level.txt
CubaCrawler-1.0.0.dist-info/RECORD
