Metadata-Version: 2.1
Name: CubaCrawler
Version: 1.0.0
Summary: This library aims to obtain information from the sites of Cuban news.
Home-page: https://github.com/fsadannn/CubaCrawler
Author: Frank Sadan Naranjo Noda, Hian Cañizares Días
Author-email: fsadannn@gmail.com, hiancdtrsnm@gmail.com
License: MIT
Download-URL: https://github.com/fsadannn/CubaCrawler/tarball/1.0.0
Platform: UNKNOWN
Classifier: Development Status :: 5 - Production/Stable
Classifier: License :: OSI Approved :: MIT License
Classifier: Programming Language :: Python :: 3.6
Classifier: Topic :: Software Development :: Libraries :: Python Modules
Requires-Dist: toml
Requires-Dist: beautifulsoup4
Requires-Dist: bs4
Requires-Dist: lxml
Requires-Dist: requests
